{
  "Epoch": {
    "ISTP.VAR_NOTES": "No VAR_NOTES attribute for variable 'Epoch'"
  },
  "brGEO": {
    "ISTP.VAR_NOTES": "No VAR_NOTES attribute for variable 'brGEO'"
  },
  "bthGEO": {
    "ISTP.VAR_NOTES": "No VAR_NOTES attribute for variable 'bthGEO'"
  },
  "bphGEO": {
    "ISTP.VAR_NOTES": "No VAR_NOTES attribute for variable 'bphGEO'"
  },
  "bpara": {
    "ISTP.VAR_NOTES": "No VAR_NOTES attribute for variable 'bpara'"
  },
  "bparp1": {
    "ISTP.VAR_NOTES": "No VAR_NOTES attribute for variable 'bparp1'"
  },
  "bparp2": {
    "ISTP.VAR_NOTES": "No VAR_NOTES attribute for variable 'bparp2'"
  },
  "brGMS": {
    "ISTP.VAR_NOTES": "No VAR_NOTES attribute for variable 'brGMS'"
  },
  "bthGMS": {
    "ISTP.VAR_NOTES": "No VAR_NOTES attribute for variable 'bthGMS'"
  },
  "bphGMS": {
    "ISTP.VAR_NOTES": "No VAR_NOTES attribute for variable 'bphGMS'"
  },
  "glon": {
    "ISTP.VAR_NOTES": "No VAR_NOTES attribute for variable 'glon'"
  },
  "glat": {
    "ISTP.VAR_NOTES": "No VAR_NOTES attribute for variable 'glat'"
  },
  "alt": {
    "ISTP.VAR_NOTES": "No VAR_NOTES attribute for variable 'alt'"
  }
}