{
  "Epoch": {
    "ISTP.VAR_NOTES": "No VAR_NOTES attribute for variable 'Epoch'"
  },
  "HV_Swp_Stat": {
    "ISTP.VAR_NOTES": "No VAR_NOTES attribute for variable 'HV_Swp_Stat'"
  },
  "Data_Quality_HV_Swp_Stat": {
    "ISTP.VAR_NOTES": "No VAR_NOTES attribute for variable 'Data_Quality_HV_Swp_Stat'"
  },
  "HV_Status": {
    "ISTP.VAR_NOTES": "No VAR_NOTES attribute for variable 'HV_Status'"
  },
  "Data_Quality_HV_Status": {
    "ISTP.VAR_NOTES": "No VAR_NOTES attribute for variable 'Data_Quality_HV_Status'"
  },
  "Spectra_Stat": {
    "ISTP.VAR_NOTES": "No VAR_NOTES attribute for variable 'Spectra_Stat'"
  },
  "Data_Quality_Spectra_Stat": {
    "ISTP.VAR_NOTES": "No VAR_NOTES attribute for variable 'Data_Quality_Spectra_Stat'"
  },
  "Time_Tag_Cmd": {
    "ISTP.VAR_NOTES": "No VAR_NOTES attribute for variable 'Time_Tag_Cmd'"
  },
  "Data_Quality_Time_Tag_Cmd": {
    "ISTP.VAR_NOTES": "No VAR_NOTES attribute for variable 'Data_Quality_Time_Tag_Cmd'"
  },
  "RTMD_A_Sense": {
    "ISTP.VAR_NOTES": "No VAR_NOTES attribute for variable 'RTMD_A_Sense'"
  },
  "Data_Quality_RTMD_A_Sense": {
    "ISTP.VAR_NOTES": "No VAR_NOTES attribute for variable 'Data_Quality_RTMD_A_Sense'"
  },
  "RTMD_B_Sense": {
    "ISTP.VAR_NOTES": "No VAR_NOTES attribute for variable 'RTMD_B_Sense'"
  },
  "Data_Quality_RTMD_B_Sense": {
    "ISTP.VAR_NOTES": "No VAR_NOTES attribute for variable 'Data_Quality_RTMD_B_Sense'"
  },
  "FDR1_Status": {
    "ISTP.VAR_NOTES": "No VAR_NOTES attribute for variable 'FDR1_Status'"
  },
  "Data_Quality_FDR1_Status": {
    "ISTP.VAR_NOTES": "No VAR_NOTES attribute for variable 'Data_Quality_FDR1_Status'"
  },
  "FDR2_Status": {
    "ISTP.VAR_NOTES": "No VAR_NOTES attribute for variable 'FDR2_Status'"
  },
  "Data_Quality_FDR2_Status": {
    "ISTP.VAR_NOTES": "No VAR_NOTES attribute for variable 'Data_Quality_FDR2_Status'"
  }
}